telegram/__init__.py
telegram/telegram.py
telegram/utils.py
pytele-0.1.0.dist-info/LICENSE
pytele-0.1.0.dist-info/WHEEL
pytele-0.1.0.dist-info/METADATA
pytele-0.1.0.dist-info/RECORD
