Metadata-Version: 2.1
Name: pytele
Version: 0.1.0
Summary: 
Author: Jordan Raychev
Author-email: jpraychev@gmail.com
Requires-Python: >=3.7,<4.0
Classifier: Programming Language :: Python :: 3
Classifier: Programming Language :: Python :: 3.7
Classifier: Programming Language :: Python :: 3.8
Classifier: Programming Language :: Python :: 3.9
Classifier: Programming Language :: Python :: 3.10
Requires-Dist: PyYAML (>=6.0,<7.0)
Requires-Dist: requests (>=2.28.1,<3.0.0)
